ros_sensor_msgs-5.5.1.data/data/include/sensor_msgs/sensor_msgs/distortion_models.hpp
ros_sensor_msgs-5.5.1.data/data/include/sensor_msgs/sensor_msgs/fill_image.hpp
ros_sensor_msgs-5.5.1.data/data/include/sensor_msgs/sensor_msgs/image_encodings.hpp
ros_sensor_msgs-5.5.1.data/data/include/sensor_msgs/sensor_msgs/point_cloud2_iterator.hpp
ros_sensor_msgs-5.5.1.data/data/include/sensor_msgs/sensor_msgs/point_cloud_conversion.hpp
ros_sensor_msgs-5.5.1.data/data/include/sensor_msgs/sensor_msgs/point_field_conversion.hpp
ros_sensor_msgs-5.5.1.data/data/include/sensor_msgs/sensor_msgs/impl/point_cloud2_iterator.hpp
ros_sensor_msgs-5.5.1.data/data/include/sensor_msgs/sensor_msgs/msg/battery_state.h
ros_sensor_msgs-5.5.1.data/data/include/sensor_msgs/sensor_msgs/msg/battery_state.hpp
ros_sensor_msgs-5.5.1.data/data/include/sensor_msgs/sensor_msgs/msg/camera_info.h
ros_sensor_msgs-5.5.1.data/data/include/sensor_msgs/sensor_msgs/msg/camera_info.hpp
ros_sensor_msgs-5.5.1.data/data/include/sensor_msgs/sensor_msgs/msg/channel_float32.h
ros_sensor_msgs-5.5.1.data/data/include/sensor_msgs/sensor_msgs/msg/channel_float32.hpp
ros_sensor_msgs-5.5.1.data/data/include/sensor_msgs/sensor_msgs/msg/compressed_image.h
ros_sensor_msgs-5.5.1.data/data/include/sensor_msgs/sensor_msgs/msg/compressed_image.hpp
ros_sensor_msgs-5.5.1.data/data/include/sensor_msgs/sensor_msgs/msg/fluid_pressure.h
ros_sensor_msgs-5.5.1.data/data/include/sensor_msgs/sensor_msgs/msg/fluid_pressure.hpp
ros_sensor_msgs-5.5.1.data/data/include/sensor_msgs/sensor_msgs/msg/illuminance.h
ros_sensor_msgs-5.5.1.data/data/include/sensor_msgs/sensor_msgs/msg/illuminance.hpp
ros_sensor_msgs-5.5.1.data/data/include/sensor_msgs/sensor_msgs/msg/image.h
ros_sensor_msgs-5.5.1.data/data/include/sensor_msgs/sensor_msgs/msg/image.hpp
ros_sensor_msgs-5.5.1.data/data/include/sensor_msgs/sensor_msgs/msg/imu.h
ros_sensor_msgs-5.5.1.data/data/include/sensor_msgs/sensor_msgs/msg/imu.hpp
ros_sensor_msgs-5.5.1.data/data/lib/python3.13/site-packages/sensor_msgs-5.5.1-py3.13.egg-info/PKG-INFO
ros_sensor_msgs-5.5.1.data/data/lib/python3.13/site-packages/sensor_msgs-5.5.1-py3.13.egg-info/SOURCES.txt
ros_sensor_msgs-5.5.1.data/data/lib/python3.13/site-packages/sensor_msgs-5.5.1-py3.13.egg-info/dependency_links.txt
ros_sensor_msgs-5.5.1.data/data/lib/python3.13/site-packages/sensor_msgs-5.5.1-py3.13.egg-info/top_level.txt
ros_sensor_msgs-5.5.1.dist-info/METADATA
ros_sensor_msgs-5.5.1.dist-info/WHEEL
ros_sensor_msgs-5.5.1.dist-info/top_level.txt
ros_sensor_msgs-5.5.1.dist-info/RECORD
ros_sensor_msgs-5.5.1.dist-info/licenses/LICENSE
